{
  "id": "d5337372-146d-4781-a8f1-4e4ca8bcf719",
  "prevId": "00000000-0000-0000-0000-000000000000",
  "version": "7",
  "dialect": "postgresql",
  "tables": {
    "public.booking": {
      "name": "booking",
      "schema": "",
      "columns": {
        "id": {
          "name": "id",
          "type": "serial",
          "primaryKey": true,
          "notNull": true
        },
        "flightId": {
          "name": "flightId",
          "type": "integer",
          "primaryKey": false,
          "notNull": true
        },
        "userId": {
          "name": "userId",
          "type": "integer",
          "primaryKey": false,
          "notNull": true
        },
        "totalCost": {
          "name": "totalCost",
          "type": "integer",
          "primaryKey": false,
          "notNull": true
        },
        "status": {
          "name": "status",
          "type": "statusEnum",
          "typeSchema": "public",
          "primaryKey": false,
          "notNull": true,
          "default": "'initiated'"
        },
        "noOfSeats": {
          "name": "noOfSeats",
          "type": "integer",
          "primaryKey": false,
          "notNull": true,
          "default": 1
        }
      },
      "indexes": {},
      "foreignKeys": {},
      "compositePrimaryKeys": {},
      "uniqueConstraints": {},
      "policies": {},
      "checkConstraints": {},
      "isRLSEnabled": false
    }
  },
  "enums": {
    "public.statusEnum": {
      "name": "statusEnum",
      "schema": "public",
      "values": [
        "booked",
        "cancelled",
        "pending",
        "initiated"
      ]
    }
  },
  "schemas": {},
  "sequences": {},
  "roles": {},
  "policies": {},
  "views": {},
  "_meta": {
    "columns": {},
    "schemas": {},
    "tables": {}
  }
}